{
"meta":{"test_sets":[],"test_metrics":[],"learn_metrics":[{"best_value":"Min","name":"MultiClass"}],"launch_mode":"Train","parameters":"","iteration_count":1000,"learn_sets":["learn"],"name":"experiment"},
"iterations":[
{"learn":[1.045813997],"iteration":0,"passed_time":0.03390342228,"remaining_time":33.86951886},
{"learn":[1.004762576],"iteration":1,"passed_time":0.06323454958,"remaining_time":31.55404024},
{"learn":[0.9732790644],"iteration":2,"passed_time":0.09354167267,"remaining_time":31.08701588},
{"learn":[0.9442498126],"iteration":3,"passed_time":0.1229930303,"remaining_time":30.62526454},
{"learn":[0.9193658562],"iteration":4,"passed_time":0.1548925785,"remaining_time":30.82362312},
{"learn":[0.8983415533],"iteration":5,"passed_time":0.1853390591,"remaining_time":30.70450412},
{"learn":[0.8807435326],"iteration":6,"passed_time":0.2157507184,"remaining_time":30.60578049},
{"learn":[0.8662879786],"iteration":7,"passed_time":0.244680533,"remaining_time":30.34038609},
{"learn":[0.8499762375],"iteration":8,"passed_time":0.2799898749,"remaining_time":30.82999623},
{"learn":[0.8387010042],"iteration":9,"passed_time":0.3115549519,"remaining_time":30.84394024},
{"learn":[0.8274637272],"iteration":10,"passed_time":0.3621204808,"remaining_time":32.55792322},
{"learn":[0.8183566945],"iteration":11,"passed_time":0.4108842036,"remaining_time":33.82946609},
{"learn":[0.8100274539],"iteration":12,"passed_time":0.4466461964,"remaining_time":33.91075353},
{"learn":[0.8031039968],"iteration":13,"passed_time":0.4735245834,"remaining_time":33.34965995},
{"learn":[0.7960179022],"iteration":14,"passed_time":0.5035034042,"remaining_time":33.06339021},
{"learn":[0.7887912279],"iteration":15,"passed_time":0.5309663145,"remaining_time":32.65442834},
{"learn":[0.7812621819],"iteration":16,"passed_time":0.5628126265,"remaining_time":32.54381246},
{"learn":[0.7775208439],"iteration":17,"passed_time":0.5933238428,"remaining_time":32.36911187},
{"learn":[0.7720913153],"iteration":18,"passed_time":0.621583598,"remaining_time":32.09334261},
{"learn":[0.7679733772],"iteration":19,"passed_time":0.6501167767,"remaining_time":31.85572206},
{"learn":[0.7645424733],"iteration":20,"passed_time":0.6778466457,"remaining_time":31.60056505},
{"learn":[0.7606991692],"iteration":21,"passed_time":0.7132175083,"remaining_time":31.70576014},
{"learn":[0.7563300971],"iteration":22,"passed_time":0.7487490684,"remaining_time":31.80555825},
{"learn":[0.7535288462],"iteration":23,"passed_time":0.7798791805,"remaining_time":31.71508667},
{"learn":[0.7510064021],"iteration":24,"passed_time":0.8078603221,"remaining_time":31.50655256},
{"learn":[0.7475692028],"iteration":25,"passed_time":0.8375148965,"remaining_time":31.37459651},
{"learn":[0.7451462761],"iteration":26,"passed_time":0.8658989068,"remaining_time":31.20443097},
{"learn":[0.741220975],"iteration":27,"passed_time":0.8911599485,"remaining_time":30.93598107},
{"learn":[0.7387234211],"iteration":28,"passed_time":0.9171327918,"remaining_time":30.70813589},
{"learn":[0.7363326193],"iteration":29,"passed_time":0.9444258949,"remaining_time":30.53643727},
{"learn":[0.7345080722],"iteration":30,"passed_time":0.9711057318,"remaining_time":30.35488562},
{"learn":[0.7323756344],"iteration":31,"passed_time":0.9976715393,"remaining_time":30.17956406},
{"learn":[0.730557953],"iteration":32,"passed_time":1.027704046,"remaining_time":30.11484279},
{"learn":[0.7280726361],"iteration":33,"passed_time":1.054955721,"remaining_time":29.97315371},
{"learn":[0.7258153111],"iteration":34,"passed_time":1.08447035,"remaining_time":29.9003968},
{"learn":[0.7237255401],"iteration":35,"passed_time":1.111361741,"remaining_time":29.75979772},
{"learn":[0.7211345474],"iteration":36,"passed_time":1.141595437,"remaining_time":29.71233528},
{"learn":[0.7194974383],"iteration":37,"passed_time":1.169255264,"remaining_time":29.60062011},
{"learn":[0.7176892605],"iteration":38,"passed_time":1.197119291,"remaining_time":29.49824714},
{"learn":[0.715939844],"iteration":39,"passed_time":1.225199944,"remaining_time":29.40479866},
{"learn":[0.7135873608],"iteration":40,"passed_time":1.257006557,"remaining_time":29.40168996},
{"learn":[0.7117950829],"iteration":41,"passed_time":1.281033281,"remaining_time":29.21975912},
{"learn":[0.7107036496],"iteration":42,"passed_time":1.309781527,"remaining_time":29.15025399},
{"learn":[0.7092997911],"iteration":43,"passed_time":1.338026515,"remaining_time":29.07166701},
{"learn":[0.7078484986],"iteration":44,"passed_time":1.366741798,"remaining_time":29.00529816},
{"learn":[0.706156323],"iteration":45,"passed_time":1.405075084,"remaining_time":29.14003544},
{"learn":[0.7047902566],"iteration":46,"passed_time":1.432128892,"remaining_time":29.03869859},
{"learn":[0.702755769],"iteration":47,"passed_time":1.46337986,"remaining_time":29.02370055},
{"learn":[0.7017019914],"iteration":48,"passed_time":1.490738304,"remaining_time":28.9324924},
{"learn":[0.7004200411],"iteration":49,"passed_time":1.51749525,"remaining_time":28.83240974},
{"learn":[0.6992224979],"iteration":50,"passed_time":1.54247597,"remaining_time":28.70215089},
{"learn":[0.6980248497],"iteration":51,"passed_time":1.567263565,"remaining_time":28.57242037},
{"learn":[0.6969124644],"iteration":52,"passed_time":1.592375518,"remaining_time":28.45244558},
{"learn":[0.6955865743],"iteration":53,"passed_time":1.621449127,"remaining_time":28.40538656},
{"learn":[0.694243361],"iteration":54,"passed_time":1.649693631,"remaining_time":28.34473602},
{"learn":[0.693127726],"iteration":55,"passed_time":1.672809357,"remaining_time":28.1987863},
{"learn":[0.6922026978],"iteration":56,"passed_time":1.702005896,"remaining_time":28.15774667},
{"learn":[0.6910181876],"iteration":57,"passed_time":1.728937787,"remaining_time":28.0803344},
{"learn":[0.6900180773],"iteration":58,"passed_time":1.752934703,"remaining_time":27.95782297},
{"learn":[0.6888796956],"iteration":59,"passed_time":1.781645101,"remaining_time":27.91243991},
{"learn":[0.6876981598],"iteration":60,"passed_time":1.809411989,"remaining_time":27.85307964},
{"learn":[0.6867694427],"iteration":61,"passed_time":1.83729894,"remaining_time":27.79655493},
{"learn":[0.6858096956],"iteration":62,"passed_time":1.866319635,"remaining_time":27.75780156},
{"learn":[0.68494814],"iteration":63,"passed_time":1.894308134,"remaining_time":27.70425646},
{"learn":[0.6834902288],"iteration":64,"passed_time":1.924103444,"remaining_time":27.677488},
{"learn":[0.6824409126],"iteration":65,"passed_time":1.951282609,"remaining_time":27.6136054},
{"learn":[0.6819879342],"iteration":66,"passed_time":1.979123207,"remaining_time":27.56002914},
{"learn":[0.6810720747],"iteration":67,"passed_time":2.005280358,"remaining_time":27.48413667},
{"learn":[0.6800490042],"iteration":68,"passed_time":2.034148327,"remaining_time":27.4462622},
{"learn":[0.6793927438],"iteration":69,"passed_time":2.063773594,"remaining_time":27.41870633},
{"learn":[0.6788081412],"iteration":70,"passed_time":2.092143438,"remaining_time":27.37466555},
{"learn":[0.6777744529],"iteration":71,"passed_time":2.12410882,"remaining_time":27.37740256},
{"learn":[0.6770109003],"iteration":72,"passed_time":2.154992515,"remaining_time":27.3654529},
{"learn":[0.6761990754],"iteration":73,"passed_time":2.193119533,"remaining_time":27.44363091},
{"learn":[0.6756521202],"iteration":74,"passed_time":2.231686944,"remaining_time":27.52413898},
{"learn":[0.6748694275],"iteration":75,"passed_time":2.266467979,"remaining_time":27.55547912},
{"learn":[0.6742326992],"iteration":76,"passed_time":2.298905688,"remaining_time":27.55701234},
{"learn":[0.6732961999],"iteration":77,"passed_time":2.333054951,"remaining_time":27.57790596},
{"learn":[0.6726899601],"iteration":78,"passed_time":2.363670788,"remaining_time":27.5562126},
{"learn":[0.6720391994],"iteration":79,"passed_time":2.396274645,"remaining_time":27.55715841},
{"learn":[0.6713379095],"iteration":80,"passed_time":2.425770255,"remaining_time":27.52201068},
{"learn":[0.6704854693],"iteration":81,"passed_time":2.455990065,"remaining_time":27.49510828},
{"learn":[0.6698748151],"iteration":82,"passed_time":2.484924689,"remaining_time":27.45392698},
{"learn":[0.669234107],"iteration":83,"passed_time":2.512557228,"remaining_time":27.39883834},
{"learn":[0.6682992831],"iteration":84,"passed_time":2.537273433,"remaining_time":27.31300225},
{"learn":[0.6670562139],"iteration":85,"passed_time":2.564633282,"remaining_time":27.25668395},
{"learn":[0.6661279321],"iteration":86,"passed_time":2.590422959,"remaining_time":27.18455358},
{"learn":[0.6656615332],"iteration":87,"passed_time":2.614803661,"remaining_time":27.09887431},
{"learn":[0.6648465426],"iteration":88,"passed_time":2.637587041,"remaining_time":26.99822241},
{"learn":[0.6640996465],"iteration":89,"passed_time":2.660990492,"remaining_time":26.90557053},
{"learn":[0.6635112686],"iteration":90,"passed_time":2.688290522,"remaining_time":26.85336356},
{"learn":[0.662866079],"iteration":91,"passed_time":2.713258305,"remaining_time":26.77867979},
{"learn":[0.6623948648],"iteration":92,"passed_time":2.737983907,"remaining_time":26.70270327},
{"learn":[0.6618977109],"iteration":93,"passed_time":2.767040682,"remaining_time":26.66956231},
{"learn":[0.6609226341],"iteration":94,"passed_time":2.796746342,"remaining_time":26.64268883},
{"learn":[0.659853664],"iteration":95,"passed_time":2.829169132,"remaining_time":26.64134266},
{"learn":[0.6592536395],"iteration":96,"passed_time":2.858135947,"remaining_time":26.6071831},
{"learn":[0.658680633],"iteration":97,"passed_time":2.89063817,"remaining_time":26.60566968},
{"learn":[0.6579700975],"iteration":98,"passed_time":2.919681008,"remaining_time":26.57204635},
{"learn":[0.6571873809],"iteration":99,"passed_time":2.945526913,"remaining_time":26.50974222},
{"learn":[0.6566536448],"iteration":100,"passed_time":3.004159382,"remaining_time":26.73999292},
{"learn":[0.6557464448],"iteration":101,"passed_time":3.045929226,"remaining_time":26.81612201},
{"learn":[0.6550003406],"iteration":102,"passed_time":3.075383644,"remaining_time":26.78270999},
{"learn":[0.6544391971],"iteration":103,"passed_time":3.104440969,"remaining_time":26.74595296},
{"learn":[0.653877644],"iteration":104,"passed_time":3.13614056,"remaining_time":26.73186477},
{"learn":[0.6531541841],"iteration":105,"passed_time":3.167399465,"remaining_time":26.71372756},
{"learn":[0.6525070122],"iteration":106,"passed_time":3.198904243,"remaining_time":26.69739709},
{"learn":[0.6521140685],"iteration":107,"passed_time":3.227285862,"remaining_time":26.65499064},
{"learn":[0.6514529674],"iteration":108,"passed_time":3.256895372,"remaining_time":26.62287868},
{"learn":[0.6508893727],"iteration":109,"passed_time":3.285584773,"remaining_time":26.58336771},
{"learn":[0.650325239],"iteration":110,"passed_time":3.313922222,"remaining_time":26.54123293},
{"learn":[0.6497187569],"iteration":111,"passed_time":3.33999551,"remaining_time":26.48139297},
{"learn":[0.6491180734],"iteration":112,"passed_time":3.370860946,"remaining_time":26.4597669},
{"learn":[0.6484248655],"iteration":113,"passed_time":3.402088441,"remaining_time":26.44079262},
{"learn":[0.6476437792],"iteration":114,"passed_time":3.427210282,"remaining_time":26.37461826},
{"learn":[0.6468918596],"iteration":115,"passed_time":3.454638864,"remaining_time":26.32673065},
{"learn":[0.646319057],"iteration":116,"passed_time":3.478915716,"remaining_time":26.25540664},
{"learn":[0.6452621639],"iteration":117,"passed_time":3.508753672,"remaining_time":26.22644694},
{"learn":[0.644705025],"iteration":118,"passed_time":3.534615584,"remaining_time":26.16803638},
{"learn":[0.6442949567],"iteration":119,"passed_time":3.565407563,"remaining_time":26.14632213},
{"learn":[0.6436771134],"iteration":120,"passed_time":3.598249006,"remaining_time":26.13934609},
{"learn":[0.6430916947],"iteration":121,"passed_time":3.627822841,"remaining_time":26.10842995},
{"learn":[0.6423259297],"iteration":122,"passed_time":3.655665735,"remaining_time":26.0651939},
{"learn":[0.6418447759],"iteration":123,"passed_time":3.680738501,"remaining_time":26.00263651},
{"learn":[0.6412470631],"iteration":124,"passed_time":3.710536205,"remaining_time":25.97375343},
{"learn":[0.6407685299],"iteration":125,"passed_time":3.737415302,"remaining_time":25.9246109},
{"learn":[0.6402830074],"iteration":126,"passed_time":3.76242304,"remaining_time":25.86295523},
{"learn":[0.6397080508],"iteration":127,"passed_time":3.788433228,"remaining_time":25.80870137},
{"learn":[0.6389804879],"iteration":128,"passed_time":3.816530871,"remaining_time":25.76897976},
{"learn":[0.6383246834],"iteration":129,"passed_time":3.839644086,"remaining_time":25.69607965},
{"learn":[0.6379994643],"iteration":130,"passed_time":3.867282141,"remaining_time":25.65395557},
{"learn":[0.6374025042],"iteration":131,"passed_time":3.890427388,"remaining_time":25.58250737},
{"learn":[0.6370143381],"iteration":132,"passed_time":3.912397532,"remaining_time":25.50412526},
{"learn":[0.6365212985],"iteration":133,"passed_time":3.938290409,"remaining_time":25.45193653},
{"learn":[0.6360456844],"iteration":134,"passed_time":3.961389466,"remaining_time":25.38223621},
{"learn":[0.6357026889],"iteration":135,"passed_time":3.985207378,"remaining_time":25.31778805},
{"learn":[0.6351980179],"iteration":136,"passed_time":4.009322933,"remaining_time":25.25580796},
{"learn":[0.6345989117],"iteration":137,"passed_time":4.036379956,"remaining_time":25.21275016},
{"learn":[0.6340913499],"iteration":138,"passed_time":4.06058352,"remaining_time":25.15224756},
{"learn":[0.6335879919],"iteration":139,"passed_time":4.087312039,"remaining_time":25.10777395},
{"learn":[0.6331289026],"iteration":140,"passed_time":4.115258749,"remaining_time":25.07097351},
{"learn":[0.6323852625],"iteration":141,"passed_time":4.143002232,"remaining_time":25.03306983},
{"learn":[0.6318436072],"iteration":142,"passed_time":4.167067203,"remaining_time":24.97326289},
{"learn":[0.6311223977],"iteration":143,"passed_time":4.19779021,"remaining_time":24.95353069},
{"learn":[0.6304053287],"iteration":144,"passed_time":4.221455713,"remaining_time":24.89203196},
{"learn":[0.6298985005],"iteration":145,"passed_time":4.247066592,"remaining_time":24.84243061},
{"learn":[0.6293370433],"iteration":146,"passed_time":4.275675981,"remaining_time":24.81055518},
{"learn":[0.6287572253],"iteration":147,"passed_time":4.300570078,"remaining_time":24.75733586},
{"learn":[0.6283139067],"iteration":148,"passed_time":4.326082066,"remaining_time":24.70802576},
{"learn":[0.6275967609],"iteration":149,"passed_time":4.355663398,"remaining_time":24.68209259},
{"learn":[0.6272173409],"iteration":150,"passed_time":4.385711204,"remaining_time":24.65873385},
{"learn":[0.6267885317],"iteration":151,"passed_time":4.409482774,"remaining_time":24.60027232},
{"learn":[0.626217705],"iteration":152,"passed_time":4.433429814,"remaining_time":24.54323564},
{"learn":[0.6255653407],"iteration":153,"passed_time":4.46323655,"remaining_time":24.51881897},
{"learn":[0.6251007731],"iteration":154,"passed_time":4.488288529,"remaining_time":24.46841166},
{"learn":[0.6244861092],"iteration":155,"passed_time":4.513650656,"remaining_time":24.42000739},
{"learn":[0.6241239721],"iteration":156,"passed_time":4.536843059,"remaining_time":24.36024649},
{"learn":[0.6236862611],"iteration":157,"passed_time":4.56148071,"remaining_time":24.30865036},
{"learn":[0.6231788886],"iteration":158,"passed_time":4.585527684,"remaining_time":24.25426907},
{"learn":[0.6227952002],"iteration":159,"passed_time":4.608822676,"remaining_time":24.19631905},
{"learn":[0.6224323347],"iteration":160,"passed_time":4.634304598,"remaining_time":24.15019601},
{"learn":[0.6219176564],"iteration":161,"passed_time":4.660070435,"remaining_time":24.10579645},
{"learn":[0.621678355],"iteration":162,"passed_time":4.683281852,"remaining_time":24.04850865},
{"learn":[0.6212299856],"iteration":163,"passed_time":4.710316856,"remaining_time":24.01112739},
{"learn":[0.6208644085],"iteration":164,"passed_time":4.738400819,"remaining_time":23.9791799},
{"learn":[0.6202226355],"iteration":165,"passed_time":4.762931247,"remaining_time":23.92942566},
{"learn":[0.6198761936],"iteration":166,"passed_time":4.786830771,"remaining_time":23.87682654},
{"learn":[0.6193065879],"iteration":167,"passed_time":4.8112495,"remaining_time":23.82714038},
{"learn":[0.6189044746],"iteration":168,"passed_time":4.836586185,"remaining_time":23.78226698},
{"learn":[0.6185870887],"iteration":169,"passed_time":4.860885288,"remaining_time":23.73255758},
{"learn":[0.6182303858],"iteration":170,"passed_time":4.884433394,"remaining_time":23.67950458},
{"learn":[0.6177911493],"iteration":171,"passed_time":4.912108227,"remaining_time":23.64666053},
{"learn":[0.6173549925],"iteration":172,"passed_time":4.937774621,"remaining_time":23.60427521},
{"learn":[0.6169964723],"iteration":173,"passed_time":4.962002777,"remaining_time":23.55525456},
{"learn":[0.6166302695],"iteration":174,"passed_time":4.986130256,"remaining_time":23.50604263},
{"learn":[0.6162835742],"iteration":175,"passed_time":5.009592468,"remaining_time":23.4540011},
{"learn":[0.6159742735],"iteration":176,"passed_time":5.032496238,"remaining_time":23.3996859},
{"learn":[0.6156255034],"iteration":177,"passed_time":5.060947503,"remaining_time":23.37134184},
{"learn":[0.615143867],"iteration":178,"passed_time":5.089882835,"remaining_time":23.3452168},
{"learn":[0.6148761769],"iteration":179,"passed_time":5.114305026,"remaining_time":23.29850067},
{"learn":[0.6144671504],"iteration":180,"passed_time":5.14071315,"remaining_time":23.26101696},
{"learn":[0.6140525304],"iteration":181,"passed_time":5.167396533,"remaining_time":23.22489211},
{"learn":[0.6137298657],"iteration":182,"passed_time":5.195787392,"remaining_time":23.19649344},
{"learn":[0.6132563969],"iteration":183,"passed_time":5.233603374,"remaining_time":23.20989323},
{"learn":[0.612789235],"iteration":184,"passed_time":5.27183879,"remaining_time":23.2245871},
{"learn":[0.6122100413],"iteration":185,"passed_time":5.303189537,"remaining_time":23.20858217},
{"learn":[0.6119655157],"iteration":186,"passed_time":5.329922198,"remaining_time":23.17233555},
{"learn":[0.6115677211],"iteration":187,"passed_time":5.356665319,"remaining_time":23.13623531},
{"learn":[0.6112430478],"iteration":188,"passed_time":5.383414673,"remaining_time":23.10026084},
{"learn":[0.6108857305],"iteration":189,"passed_time":5.416393006,"remaining_time":23.0909386},
{"learn":[0.6104437452],"iteration":190,"passed_time":5.443006808,"remaining_time":23.05441103},
{"learn":[0.6100855304],"iteration":191,"passed_time":5.470260542,"remaining_time":23.02067978},
{"learn":[0.6096522526],"iteration":192,"passed_time":5.495282871,"remaining_time":22.97768537},
{"learn":[0.6091496887],"iteration":193,"passed_time":5.536685129,"remaining_time":23.00292894},
{"learn":[0.6088352378],"iteration":194,"passed_time":5.576929353,"remaining_time":23.02270835},
{"learn":[0.6085852781],"iteration":195,"passed_time":5.614033156,"remaining_time":23.02899315},
{"learn":[0.6083975281],"iteration":196,"passed_time":5.637765138,"remaining_time":22.98033201},
{"learn":[0.6081296433],"iteration":197,"passed_time":5.661575053,"remaining_time":22.93223835},
{"learn":[0.6077240455],"iteration":198,"passed_time":5.687122249,"remaining_time":22.89138152},
{"learn":[0.6073748969],"iteration":199,"passed_time":5.713941099,"remaining_time":22.8557644},
{"learn":[0.607070852],"iteration":200,"passed_time":5.737693149,"remaining_time":22.80804391},
{"learn":[0.606764492],"iteration":201,"passed_time":5.762878597,"remaining_time":22.76622337},
{"learn":[0.606446675],"iteration":202,"passed_time":5.788407953,"remaining_time":22.72591694},
{"learn":[0.6061209045],"iteration":203,"passed_time":5.812740544,"remaining_time":22.68108565},
{"learn":[0.6057612428],"iteration":204,"passed_time":5.840100412,"remaining_time":22.64819428},
{"learn":[0.6054134448],"iteration":205,"passed_time":5.864425582,"remaining_time":22.60365977},
{"learn":[0.6050360579],"iteration":206,"passed_time":5.89495336,"remaining_time":22.5830822},
{"learn":[0.6047244747],"iteration":207,"passed_time":5.919945162,"remaining_time":22.54132966},
{"learn":[0.6044234769],"iteration":208,"passed_time":5.946583136,"remaining_time":22.50596775},
{"learn":[0.6041457996],"iteration":209,"passed_time":5.970988327,"remaining_time":22.46228942},
{"learn":[0.6039369076],"iteration":210,"passed_time":5.996374277,"remaining_time":22.42246116},
{"learn":[0.6035164095],"iteration":211,"passed_time":6.022550895,"remaining_time":22.38570804},
{"learn":[0.6031829182],"iteration":212,"passed_time":6.047787117,"remaining_time":22.34557963},
{"learn":[0.6027594985],"iteration":213,"passed_time":6.075626343,"remaining_time":22.31515096},
{"learn":[0.602338426],"iteration":214,"passed_time":6.104322543,"remaining_time":22.28787533},
{"learn":[0.6021992722],"iteration":215,"passed_time":6.135276693,"remaining_time":22.26878207},
{"learn":[0.601726247],"iteration":216,"passed_time":6.173464139,"remaining_time":22.27567936},
{"learn":[0.6013019057],"iteration":217,"passed_time":6.208484269,"remaining_time":22.27080137},
{"learn":[0.6010794409],"iteration":218,"passed_time":6.241315247,"remaining_time":22.25784113},
{"learn":[0.60088841],"iteration":219,"passed_time":6.272051292,"remaining_time":22.23727276},
{"learn":[0.6006526268],"iteration":220,"passed_time":6.300521231,"remaining_time":22.20862461},
{"learn":[0.6002515667],"iteration":221,"passed_time":6.330992201,"remaining_time":22.18699069},
{"learn":[0.5999964491],"iteration":222,"passed_time":6.362638282,"remaining_time":22.16937195},
{"learn":[0.5996131923],"iteration":223,"passed_time":6.387633021,"remaining_time":22.12858582},
{"learn":[0.5992073649],"iteration":224,"passed_time":6.420522548,"remaining_time":22.11513322},
{"learn":[0.5989030646],"iteration":225,"passed_time":6.451236307,"remaining_time":22.09405709},
{"learn":[0.5986076246],"iteration":226,"passed_time":6.482611324,"remaining_time":22.07514781},
{"learn":[0.5983484342],"iteration":227,"passed_time":6.514163426,"remaining_time":22.05672879},
{"learn":[0.598064104],"iteration":228,"passed_time":6.542763258,"remaining_time":22.02825533},
{"learn":[0.5976715777],"iteration":229,"passed_time":6.571778598,"remaining_time":22.00117183},
{"learn":[0.597403454],"iteration":230,"passed_time":6.599901155,"remaining_time":21.97109952},
{"learn":[0.5971613978],"iteration":231,"passed_time":6.629495154,"remaining_time":21.94591499},
{"learn":[0.5969293714],"iteration":232,"passed_time":6.65542534,"remaining_time":21.90863191},
{"learn":[0.596597121],"iteration":233,"passed_time":6.685517822,"remaining_time":21.88507116},
{"learn":[0.5963424491],"iteration":234,"passed_time":6.718423585,"remaining_time":21.87061295},
{"learn":[0.596146463],"iteration":235,"passed_time":6.74590496,"remaining_time":21.83843809},
{"learn":[0.5958456651],"iteration":236,"passed_time":6.773813335,"remaining_time":21.80767753},
{"learn":[0.5956275167],"iteration":237,"passed_time":6.804468499,"remaining_time":21.78573528},
{"learn":[0.5953195831],"iteration":238,"passed_time":6.832296009,"remaining_time":21.75471658},
{"learn":[0.5950917534],"iteration":239,"passed_time":6.862243472,"remaining_time":21.73043766},
{"learn":[0.5947202058],"iteration":240,"passed_time":6.892805068,"remaining_time":21.70804584},
{"learn":[0.594445044],"iteration":241,"passed_time":6.921247974,"remaining_time":21.67895026},
{"learn":[0.5941560543],"iteration":242,"passed_time":6.949945358,"remaining_time":21.65065282},
{"learn":[0.5939321835],"iteration":243,"passed_time":6.97823134,"remaining_time":21.62107743},
{"learn":[0.5935958235],"iteration":244,"passed_time":7.008330853,"remaining_time":21.5971012},
{"learn":[0.5933418578],"iteration":245,"passed_time":7.034866705,"remaining_time":21.56215242},
{"learn":[0.593214248],"iteration":246,"passed_time":7.064258114,"remaining_time":21.53597717},
{"learn":[0.5930525809],"iteration":247,"passed_time":7.092245531,"remaining_time":21.50551871},
{"learn":[0.5928067413],"iteration":248,"passed_time":7.11988176,"remaining_time":21.47402089},
{"learn":[0.5925973619],"iteration":249,"passed_time":7.146673532,"remaining_time":21.4400206},
{"learn":[0.5923031486],"iteration":250,"passed_time":7.173662026,"remaining_time":21.40666477},
{"learn":[0.5918837801],"iteration":251,"passed_time":7.198337801,"remaining_time":21.36649474},
{"learn":[0.5917862185],"iteration":252,"passed_time":7.223746785,"remaining_time":21.32861205},
{"learn":[0.5914445251],"iteration":253,"passed_time":7.252171526,"remaining_time":21.29968488},
{"learn":[0.5911987616],"iteration":254,"passed_time":7.278583633,"remaining_time":21.26488159},
{"learn":[0.5908950214],"iteration":255,"passed_time":7.309390615,"remaining_time":21.24291647},
{"learn":[0.5906124163],"iteration":256,"passed_time":7.335805296,"remaining_time":21.20818418},
{"learn":[0.5903857474],"iteration":257,"passed_time":7.363044576,"remaining_time":21.17588789},
{"learn":[0.5899585811],"iteration":258,"passed_time":7.39124338,"remaining_time":21.14637585},
{"learn":[0.5897946803],"iteration":259,"passed_time":7.417831527,"remaining_time":21.11228973},
{"learn":[0.5895571663],"iteration":260,"passed_time":7.444044235,"remaining_time":21.07719805},
{"learn":[0.5894372662],"iteration":261,"passed_time":7.471380788,"remaining_time":21.04533978},
{"learn":[0.589182972],"iteration":262,"passed_time":7.499604348,"remaining_time":21.01600154},
{"learn":[0.5889481785],"iteration":263,"passed_time":7.52601465,"remaining_time":20.9816166},
{"learn":[0.5888012442],"iteration":264,"passed_time":7.552800378,"remaining_time":20.94833312},
{"learn":[0.588770634],"iteration":265,"passed_time":7.579416363,"remaining_time":20.91463011},
{"learn":[0.5884981209],"iteration":266,"passed_time":7.611567991,"remaining_time":20.89617729},
{"learn":[0.5882277862],"iteration":267,"passed_time":7.639815572,"remaining_time":20.86695895},
{"learn":[0.587924655],"iteration":268,"passed_time":7.66795353,"remaining_time":20.83744993},
{"learn":[0.5876334506],"iteration":269,"passed_time":7.6951892,"remaining_time":20.80551154},
{"learn":[0.5874518335],"iteration":270,"passed_time":7.720236834,"remaining_time":20.76772196},
{"learn":[0.5871087447],"iteration":271,"passed_time":7.746970912,"remaining_time":20.73453979},
{"learn":[0.5868538196],"iteration":272,"passed_time":7.774111499,"remaining_time":20.7024874},
{"learn":[0.5866873931],"iteration":273,"passed_time":7.800736722,"remaining_time":20.66910533},
{"learn":[0.5866218672],"iteration":274,"passed_time":7.824347832,"remaining_time":20.6278261},
{"learn":[0.5862211848],"iteration":275,"passed_time":7.852094113,"remaining_time":20.59752224},
{"learn":[0.5860095003],"iteration":276,"passed_time":7.879678614,"remaining_time":20.56681458},
{"learn":[0.585757587],"iteration":277,"passed_time":7.909996411,"remaining_time":20.54322809},
{"learn":[0.5854296915],"iteration":278,"passed_time":7.940692743,"remaining_time":20.52057157},
{"learn":[0.5850584796],"iteration":279,"passed_time":7.966471665,"remaining_time":20.48521285},
{"learn":[0.5849619196],"iteration":280,"passed_time":7.992918666,"remaining_time":20.45163175},
{"learn":[0.5848453588],"iteration":281,"passed_time":8.017711112,"remaining_time":20.41388858},
{"learn":[0.5846935654],"iteration":282,"passed_time":8.042658566,"remaining_time":20.37662965},
{"learn":[0.5844117226],"iteration":283,"passed_time":8.072816452,"remaining_time":20.35259359},
{"learn":[0.5841272053],"iteration":284,"passed_time":8.114235706,"remaining_time":20.35676677},
{"learn":[0.5839910098],"iteration":285,"passed_time":8.14590454,"remaining_time":20.33627917},
{"learn":[0.5836978718],"iteration":286,"passed_time":8.181447563,"remaining_time":20.32533837},
{"learn":[0.5835854447],"iteration":287,"passed_time":8.222466473,"remaining_time":20.32776434},
{"learn":[0.5834358756],"iteration":288,"passed_time":8.26020515,"remaining_time":20.32181959},
{"learn":[0.583114539],"iteration":289,"passed_time":8.299946917,"remaining_time":20.32055969},
{"learn":[0.5827144963],"iteration":290,"passed_time":8.34474283,"remaining_time":20.33134937},
{"learn":[0.5824339955],"iteration":291,"passed_time":8.386569337,"remaining_time":20.33455853},
{"learn":[0.5821402265],"iteration":292,"passed_time":8.42640364,"remaining_time":20.33265315},
{"learn":[0.5817951413],"iteration":293,"passed_time":8.463393771,"remaining_time":20.32365987},
{"learn":[0.5815987837],"iteration":294,"passed_time":8.493261969,"remaining_time":20.29745657},
{"learn":[0.5813227434],"iteration":295,"passed_time":8.529126857,"remaining_time":20.2854909},
{"learn":[0.581089319],"iteration":296,"passed_time":8.557537196,"remaining_time":20.25571936},
{"learn":[0.580752003],"iteration":297,"passed_time":8.595311814,"remaining_time":20.24801642},
{"learn":[0.58060283],"iteration":298,"passed_time":8.632930921,"remaining_time":20.23974774},
{"learn":[0.5803981173],"iteration":299,"passed_time":8.672237456,"remaining_time":20.23522073},
{"learn":[0.5802327742],"iteration":300,"passed_time":8.706727567,"remaining_time":20.21927764},
{"learn":[0.5800876032],"iteration":301,"passed_time":8.760696645,"remaining_time":20.24823264},
{"learn":[0.5799040077],"iteration":302,"passed_time":8.821249822,"remaining_time":20.29178589},
{"learn":[0.5796017652],"iteration":303,"passed_time":8.855476289,"remaining_time":20.27437993},
{"learn":[0.5793938211],"iteration":304,"passed_time":8.888567875,"remaining_time":20.25427762},
{"learn":[0.5791532831],"iteration":305,"passed_time":8.917166432,"remaining_time":20.22390034},
{"learn":[0.5789717002],"iteration":306,"passed_time":8.943983978,"remaining_time":20.18951432},
{"learn":[0.5788014207],"iteration":307,"passed_time":8.973972566,"remaining_time":20.162302},
{"learn":[0.5785956971],"iteration":308,"passed_time":9.00591181,"remaining_time":20.13943385},
{"learn":[0.5781314365],"iteration":309,"passed_time":9.04395537,"remaining_time":20.13009421},
{"learn":[0.5780026349],"iteration":310,"passed_time":9.073724978,"remaining_time":20.10223958},
{"learn":[0.5777780243],"iteration":311,"passed_time":9.106680679,"remaining_time":20.08139842},
{"learn":[0.5775268835],"iteration":312,"passed_time":9.140572793,"remaining_time":20.06253517},
{"learn":[0.5771669317],"iteration":313,"passed_time":9.203918426,"remaining_time":20.1079237},
{"learn":[0.5770758377],"iteration":314,"passed_time":9.279077498,"remaining_time":20.17831139},
{"learn":[0.5768080256],"iteration":315,"passed_time":9.317969983,"remaining_time":20.1692768},
{"learn":[0.576563813],"iteration":316,"passed_time":9.366564242,"remaining_time":20.18095703},
{"learn":[0.5763270789],"iteration":317,"passed_time":9.404093415,"remaining_time":20.16852739},
{"learn":[0.5761098379],"iteration":318,"passed_time":9.437200888,"remaining_time":20.14650096},
{"learn":[0.5759102312],"iteration":319,"passed_time":9.469866724,"remaining_time":20.12346679},
{"learn":[0.5757222435],"iteration":320,"passed_time":9.513642919,"remaining_time":20.12387396},
{"learn":[0.5755829879],"iteration":321,"passed_time":9.554044118,"remaining_time":20.11690035},
{"learn":[0.5753549219],"iteration":322,"passed_time":9.592553236,"remaining_time":20.105754},
{"learn":[0.5751185814],"iteration":323,"passed_time":9.629249617,"remaining_time":20.09065661},
{"learn":[0.5748170621],"iteration":324,"passed_time":9.663195242,"remaining_time":20.06971319},
{"learn":[0.574418854],"iteration":325,"passed_time":9.698832657,"remaining_time":20.05218776},
{"learn":[0.5741968133],"iteration":326,"passed_time":9.729134745,"remaining_time":20.0235709},
{"learn":[0.5738856462],"iteration":327,"passed_time":9.754778352,"remaining_time":19.98539955},
{"learn":[0.5736513838],"iteration":328,"passed_time":9.781145943,"remaining_time":19.94878093},
{"learn":[0.573426791],"iteration":329,"passed_time":9.809257421,"remaining_time":19.91576507},
{"learn":[0.5731778162],"iteration":330,"passed_time":9.835590133,"remaining_time":19.87918368},
{"learn":[0.5731325995],"iteration":331,"passed_time":9.859477544,"remaining_time":19.83774397},
{"learn":[0.5729024199],"iteration":332,"passed_time":9.888058674,"remaining_time":19.80581122},
{"learn":[0.5726905018],"iteration":333,"passed_time":9.913293042,"remaining_time":19.76722505},
{"learn":[0.5725239491],"iteration":334,"passed_time":9.9395326,"remaining_time":19.73071397},
{"learn":[0.5723038827],"iteration":335,"passed_time":9.967886905,"remaining_time":19.69844317},
{"learn":[0.572139234],"iteration":336,"passed_time":9.992674499,"remaining_time":19.65917861},
{"learn":[0.57184223],"iteration":337,"passed_time":10.017471,"remaining_time":19.62001716},
{"learn":[0.571669359],"iteration":338,"passed_time":10.04103845,"remaining_time":19.578544},
{"learn":[0.5713682564],"iteration":339,"passed_time":10.07004929,"remaining_time":19.54774274},
{"learn":[0.5711973544],"iteration":340,"passed_time":10.10026064,"remaining_time":19.51927203},
{"learn":[0.5710210035],"iteration":341,"passed_time":10.12539468,"remaining_time":19.48102251},
{"learn":[0.5708475375],"iteration":342,"passed_time":10.15180632,"remaining_time":19.44529665},
{"learn":[0.5706447327],"iteration":343,"passed_time":10.18094323,"remaining_time":19.41482198},
{"learn":[0.5705071663],"iteration":344,"passed_time":10.20395947,"remaining_time":19.37273465},
{"learn":[0.5703284371],"iteration":345,"passed_time":10.22778603,"remaining_time":19.3322892},
{"learn":[0.5701655496],"iteration":346,"passed_time":10.25452587,"remaining_time":19.29742189},
{"learn":[0.5700413053],"iteration":347,"passed_time":10.27829158,"remaining_time":19.25702905},
{"learn":[0.5698716695],"iteration":348,"passed_time":10.30276431,"remaining_time":19.21805033},
{"learn":[0.5696834174],"iteration":349,"passed_time":10.326244,"remaining_time":19.17731029},
{"learn":[0.5694528455],"iteration":350,"passed_time":10.35386237,"remaining_time":19.14432102},
{"learn":[0.5693595643],"iteration":351,"passed_time":10.37704685,"remaining_time":19.10319988},
{"learn":[0.5692421876],"iteration":352,"passed_time":10.40524742,"remaining_time":19.07137417},
{"learn":[0.5690269205],"iteration":353,"passed_time":10.43407982,"remaining_time":19.04072193},
{"learn":[0.5688572435],"iteration":354,"passed_time":10.46113319,"remaining_time":19.00684763},
{"learn":[0.5686154518],"iteration":355,"passed_time":10.48637449,"remaining_time":18.96973363},
{"learn":[0.5683500629],"iteration":356,"passed_time":10.51648775,"remaining_time":18.94146112},
{"learn":[0.5681444559],"iteration":357,"passed_time":10.54256441,"remaining_time":18.90593952},
{"learn":[0.5679144159],"iteration":358,"passed_time":10.57212625,"remaining_time":18.87669338},
{"learn":[0.5677896036],"iteration":359,"passed_time":10.60325821,"remaining_time":18.85023681},
{"learn":[0.5676822558],"iteration":360,"passed_time":10.63286213,"remaining_time":18.82104958},
{"learn":[0.5675425968],"iteration":361,"passed_time":10.65978928,"remaining_time":18.78714243},
{"learn":[0.5673263745],"iteration":362,"passed_time":10.689298,"remaining_time":18.75780393},
{"learn":[0.5671718225],"iteration":363,"passed_time":10.72743573,"remaining_time":18.74354155},
{"learn":[0.5670689027],"iteration":364,"passed_time":10.75671754,"remaining_time":18.71374148},
{"learn":[0.5668988507],"iteration":365,"passed_time":10.79116866,"remaining_time":18.69289872},
{"learn":[0.5666244774],"iteration":366,"passed_time":10.82619746,"remaining_time":18.67297819},
{"learn":[0.5664340259],"iteration":367,"passed_time":10.85627701,"remaining_time":18.64447573},
{"learn":[0.5662564082],"iteration":368,"passed_time":10.88663744,"remaining_time":18.61644505},
{"learn":[0.5660815853],"iteration":369,"passed_time":10.91569458,"remaining_time":18.58618267},
{"learn":[0.5658639088],"iteration":370,"passed_time":10.94391491,"remaining_time":18.55450803},
{"learn":[0.5657247348],"iteration":371,"passed_time":10.96945481,"remaining_time":18.51832694},
{"learn":[0.5655307154],"iteration":372,"passed_time":10.99968017,"remaining_time":18.490079},
{"learn":[0.5654296782],"iteration":373,"passed_time":11.02402321,"remaining_time":18.45197468},
{"learn":[0.5653426614],"iteration":374,"passed_time":11.05378836,"remaining_time":18.42298061},
{"learn":[0.5651290529],"iteration":375,"passed_time":11.08055245,"remaining_time":18.38900194},
{"learn":[0.564757892],"iteration":376,"passed_time":11.11121935,"remaining_time":18.36151102},
{"learn":[0.5646255867],"iteration":377,"passed_time":11.13777814,"remaining_time":18.3272434},
{"learn":[0.5644893561],"iteration":378,"passed_time":11.17027813,"remaining_time":18.30275123},
{"learn":[0.5643025158],"iteration":379,"passed_time":11.20057561,"remaining_time":18.27462337},
{"learn":[0.564004995],"iteration":380,"passed_time":11.22966823,"remaining_time":18.2445266},
{"learn":[0.5638150401],"iteration":381,"passed_time":11.25587865,"remaining_time":18.20977226},
{"learn":[0.563606359],"iteration":382,"passed_time":11.28440448,"remaining_time":18.17879259},
{"learn":[0.5634464479],"iteration":383,"passed_time":11.31724475,"remaining_time":18.15474679},
{"learn":[0.5633405561],"iteration":384,"passed_time":11.34500621,"remaining_time":18.12254239},
{"learn":[0.5631887479],"iteration":385,"passed_time":11.37245186,"remaining_time":18.08985865},
{"learn":[0.5630851498],"iteration":386,"passed_time":11.39949822,"remaining_time":18.05656954},
{"learn":[0.5629114505],"iteration":387,"passed_time":11.4274394,"remaining_time":18.024724},
{"learn":[0.5628198617],"iteration":388,"passed_time":11.45397856,"remaining_time":17.99069639},
{"learn":[0.56270583],"iteration":389,"passed_time":11.48349823,"remaining_time":17.96136902},
{"learn":[0.5626614515],"iteration":390,"passed_time":11.51338698,"remaining_time":17.93261553},
{"learn":[0.5624181906],"iteration":391,"passed_time":11.54149197,"remaining_time":17.90108958},
{"learn":[0.5622916378],"iteration":392,"passed_time":11.56942358,"remaining_time":17.86931326},
{"learn":[0.5621116071],"iteration":393,"passed_time":11.59890671,"remaining_time":17.8399428},
{"learn":[0.5619391218],"iteration":394,"passed_time":11.62944703,"remaining_time":17.81219102},
{"learn":[0.5618404067],"iteration":395,"passed_time":11.65881321,"remaining_time":17.7826343},
{"learn":[0.5617977684],"iteration":396,"passed_time":11.68634996,"remaining_time":17.75029981},
{"learn":[0.5616245658],"iteration":397,"passed_time":11.71665999,"remaining_time":17.72218421},
{"learn":[0.5615382992],"iteration":398,"passed_time":11.741317,"remaining_time":17.68554264},
{"learn":[0.5615114053],"iteration":399,"passed_time":11.7690587,"remaining_time":17.65358805},
{"learn":[0.5614723701],"iteration":400,"passed_time":11.7958429,"remaining_time":17.62022419},
{"learn":[0.561314656],"iteration":401,"passed_time":11.83016281,"remaining_time":17.59810289},
{"learn":[0.5610860094],"iteration":402,"passed_time":11.86373063,"remaining_time":17.57480692},
{"learn":[0.5608892758],"iteration":403,"passed_time":11.9000775,"remaining_time":17.55555988},
{"learn":[0.560785674],"iteration":404,"passed_time":11.9334463,"remaining_time":17.5318532},
{"learn":[0.5606716947],"iteration":405,"passed_time":11.96802408,"remaining_time":17.50986774},
{"learn":[0.560532206],"iteration":406,"passed_time":11.99779621,"remaining_time":17.48081856},
{"learn":[0.5603441846],"iteration":407,"passed_time":12.03076924,"remaining_time":17.45641027},
{"learn":[0.5601103033],"iteration":408,"passed_time":12.06417572,"remaining_time":17.43258643},
{"learn":[0.5599531326],"iteration":409,"passed_time":12.08702021,"remaining_time":17.39351688},
{"learn":[0.5597593951],"iteration":410,"passed_time":12.11223071,"remaining_time":17.357917},
{"learn":[0.5596801562],"iteration":411,"passed_time":12.13536345,"remaining_time":17.3194022},
{"learn":[0.5595701608],"iteration":412,"passed_time":12.16070574,"remaining_time":17.28410235},
{"learn":[0.559267025],"iteration":413,"passed_time":12.18518616,"remaining_time":17.24763065},
{"learn":[0.5590053617],"iteration":414,"passed_time":12.21220046,"remaining_time":17.2147886},
{"learn":[0.5588582909],"iteration":415,"passed_time":12.23478417,"remaining_time":17.1757547},
{"learn":[0.5587639487],"iteration":416,"passed_time":12.2560479,"remaining_time":17.13495425},
{"learn":[0.5586082908],"iteration":417,"passed_time":12.29959102,"remaining_time":17.12526788},
{"learn":[0.5584556061],"iteration":418,"passed_time":12.34029964,"remaining_time":17.11148947},
{"learn":[0.5584070585],"iteration":419,"passed_time":12.36462591,"remaining_time":17.07495958},
{"learn":[0.5581849449],"iteration":420,"passed_time":12.39061986,"remaining_time":17.04078123},
{"learn":[0.5580419528],"iteration":421,"passed_time":12.42193508,"remaining_time":17.01393004},
{"learn":[0.557980917],"iteration":422,"passed_time":12.44230209,"remaining_time":16.97212365},
{"learn":[0.5577932553],"iteration":423,"passed_time":12.4707497,"remaining_time":16.94139581},
{"learn":[0.5575746165],"iteration":424,"passed_time":12.49900472,"remaining_time":16.91041815},
{"learn":[0.5575349743],"iteration":425,"passed_time":12.52164955,"remaining_time":16.871894},
{"learn":[0.5572883177],"iteration":426,"passed_time":12.55000576,"remaining_time":16.84110844},
{"learn":[0.5571142134],"iteration":427,"passed_time":12.57561111,"remaining_time":16.80665783},
{"learn":[0.5567223525],"iteration":428,"passed_time":12.60164249,"remaining_time":16.77281553},
{"learn":[0.5566728965],"iteration":429,"passed_time":12.62816819,"remaining_time":16.73966481},
{"learn":[0.5565523556],"iteration":430,"passed_time":12.65384142,"remaining_time":16.70541942},
{"learn":[0.5564252239],"iteration":431,"passed_time":12.68213068,"remaining_time":16.6746533},
{"learn":[0.5562533787],"iteration":432,"passed_time":12.71261347,"remaining_time":16.64677099},
{"learn":[0.5561080556],"iteration":433,"passed_time":12.74270919,"remaining_time":16.6183719},
{"learn":[0.5559689176],"iteration":434,"passed_time":12.77155827,"remaining_time":16.5883458},
{"learn":[0.5558685148],"iteration":435,"passed_time":12.80749404,"remaining_time":16.56749229},
{"learn":[0.5556148987],"iteration":436,"passed_time":12.83461818,"remaining_time":16.53521748},
{"learn":[0.555526724],"iteration":437,"passed_time":12.86083305,"remaining_time":16.50179949},
{"learn":[0.5554317292],"iteration":438,"passed_time":12.88985188,"remaining_time":16.4719975},
{"learn":[0.555317757],"iteration":439,"passed_time":12.91594647,"remaining_time":16.43847733},
{"learn":[0.5551237648],"iteration":440,"passed_time":12.94163029,"remaining_time":16.40447014},
{"learn":[0.5549537866],"iteration":441,"passed_time":12.96717492,"remaining_time":16.3703249},
{"learn":[0.5549048244],"iteration":442,"passed_time":12.99480503,"remaining_time":16.33884063},
{"learn":[0.5548520845],"iteration":443,"passed_time":13.06688001,"remaining_time":16.36302992},
{"learn":[0.5546894207],"iteration":444,"passed_time":13.14566629,"remaining_time":16.39515683},
{"learn":[0.5545236607],"iteration":445,"passed_time":13.23986505,"remaining_time":16.44593102},
{"learn":[0.5543349723],"iteration":446,"passed_time":13.36262261,"remaining_time":16.5313877},
{"learn":[0.5542508236],"iteration":447,"passed_time":13.48958275,"remaining_time":16.62109304},
{"learn":[0.5540142449],"iteration":448,"passed_time":13.62974826,"remaining_time":16.72603851},
{"learn":[0.55391279],"iteration":449,"passed_time":13.73618383,"remaining_time":16.78866913},
{"learn":[0.5537259768],"iteration":450,"passed_time":13.83542045,"remaining_time":16.84178676},
{"learn":[0.5535963529],"iteration":451,"passed_time":13.91299281,"remaining_time":16.86796473},
{"learn":[0.5534478318],"iteration":452,"passed_time":14.01363791,"remaining_time":16.92154512},
{"learn":[0.5532943303],"iteration":453,"passed_time":14.11380953,"remaining_time":16.97387666},
{"learn":[0.5530057013],"iteration":454,"passed_time":14.20405078,"remaining_time":17.01364324},
{"learn":[0.5528838564],"iteration":455,"passed_time":14.28076916,"remaining_time":17.03670707},
{"learn":[0.552756174],"iteration":456,"passed_time":14.36219523,"remaining_time":17.06492781},
{"learn":[0.5526105808],"iteration":457,"passed_time":14.4616713,"remaining_time":17.11403023},
{"learn":[0.5523746471],"iteration":458,"passed_time":14.53703561,"remaining_time":17.13406593},
{"learn":[0.552238137],"iteration":459,"passed_time":14.61542805,"remaining_time":17.15724163},
{"learn":[0.5520907786],"iteration":460,"passed_time":14.70044444,"remaining_time":17.18772137},
{"learn":[0.5518987433],"iteration":461,"passed_time":14.7821502,"remaining_time":17.2138459},
{"learn":[0.5516443425],"iteration":462,"passed_time":14.87276808,"remaining_time":17.24984116}
]}